.gitignore
CHANGES.txt
COPYRIGHT.txt
LICENSE.txt
README.txt
setup.cfg
setup.py
docs/.gitignore
docs/Makefile
docs/conf.py
docs/index.rst
docs/_static/exclaim.png
docs/_static/exclaim_color.png
docs/_static/info.png
docs/_static/info_color.png
docs/_static/onebit_36.png
docs/_static/onebit_38.png
docs/_static/pyramid.png
docs/_static/pyramid_epub.css
pyramid_traversalwrapper/__init__.py
pyramid_traversalwrapper/tests.py
pyramid_traversalwrapper.egg-info/PKG-INFO
pyramid_traversalwrapper.egg-info/SOURCES.txt
pyramid_traversalwrapper.egg-info/dependency_links.txt
pyramid_traversalwrapper.egg-info/entry_points.txt
pyramid_traversalwrapper.egg-info/not-zip-safe
pyramid_traversalwrapper.egg-info/requires.txt
pyramid_traversalwrapper.egg-info/top_level.txt