Metadata-Version: 1.0
Name: pyramid-traversalwrapper
Version: 0.1
Summary: An add-on for the Pyramid web framework which supplies a model graph traverser which proxies location-ignorant model objects
Home-page: http://docs.pylonshq.com
Author: Chris McDonough
Author-email: pylons-discuss@googlegroups.com
License: BSD-derived (http://www.repoze.org/LICENSE.txt)
Keywords: pylons pyramid traverser traversal proxy
Platform: UNKNOWN
Classifier: Intended Audience :: Developers
Classifier: Programming Language :: Python
